odoo/addons/web_tree_dynamic_colored_field/README.rst
odoo/addons/web_tree_dynamic_colored_field/__init__.py
odoo/addons/web_tree_dynamic_colored_field/__manifest__.py
odoo/addons/web_tree_dynamic_colored_field/demo/res_users.xml
odoo/addons/web_tree_dynamic_colored_field/i18n/es.po
odoo/addons/web_tree_dynamic_colored_field/i18n/fi.po
odoo/addons/web_tree_dynamic_colored_field/i18n/nl_NL.po
odoo/addons/web_tree_dynamic_colored_field/i18n/sl.po
odoo/addons/web_tree_dynamic_colored_field/i18n/web_tree_dynamic_colored_field.pot
odoo/addons/web_tree_dynamic_colored_field/i18n/zh_CN.po
odoo/addons/web_tree_dynamic_colored_field/readme/CONTRIBUTORS.rst
odoo/addons/web_tree_dynamic_colored_field/readme/DESCRIPTION.rst
odoo/addons/web_tree_dynamic_colored_field/readme/ROADMAP.rst
odoo/addons/web_tree_dynamic_colored_field/readme/USAGE.rst
odoo/addons/web_tree_dynamic_colored_field/static/description/icon.png
odoo/addons/web_tree_dynamic_colored_field/static/description/index.html
odoo/addons/web_tree_dynamic_colored_field/static/src/js/web_tree_dynamic_colored_field.js
odoo/addons/web_tree_dynamic_colored_field/views/web_tree_dynamic_colored_field.xml
odoo13_addon_web_tree_dynamic_colored_field-13.0.1.0.1.dev10.dist-info/METADATA
odoo13_addon_web_tree_dynamic_colored_field-13.0.1.0.1.dev10.dist-info/WHEEL
odoo13_addon_web_tree_dynamic_colored_field-13.0.1.0.1.dev10.dist-info/top_level.txt
odoo13_addon_web_tree_dynamic_colored_field-13.0.1.0.1.dev10.dist-info/RECORD
